config_setup.py
config_setup-0.7.8.dist-info/WHEEL
config_setup-0.7.8.dist-info/METADATA
config_setup-0.7.8.dist-info/RECORD
