Metadata-Version: 2.1
Name: config_setup
Version: 0.7.8
Summary: Config Setup for Python - create and save settings or configurations
Author-email: Lyubomir Ternavskiy <ternavski103@gmail.com>
Classifier: Development Status :: 4 - Beta
Classifier: Programming Language :: Python
